{
  "owner": "所有者",
  "author": "作者",
  "server_id": "服务器ID",
  "egg": "蛋类",
  "egg_info": "鸡蛋信息",
  "limits": "极限",
  "startup": "启动",
  "cpu": "CPU",
  "mem": "内存",
  "location": "地点",
  "disk": "磁盘",
  "disk_space": "磁盘空间",
  "stats": "统计",
  "databases": "数据库",
  "allocations": "分配",
  "backup_limit": "备份限制",
  "database_limit": "数据库限制",
  "allocation_limit": "分配限额",
  "unlimited": "无限",
  "server_info": "服务器信息",
  "status": "地位",
  "cpu_usage": "CPU 使用率",
  "mem_usage": "内存使用量",
  "not_available": "不详",
  "suspended": "暂停",
  "console": "{{name}} 控制台",
  "servers": "服务器",
  "connection": "联系",
  "backup": "后援",
  "backups": "备份",
  "backing_up": "备份",
  "no_backups": "该服务器没有任何备份",
  "no_servers": "该用户没有任何服务器",
  "vars": "变量",
  "email": "电子邮件",
  "locked": "锁定",
  "ignored_files": "被忽略的文件",
  "created": "创建",
  "cpu_cores": "CPU 内核",
  "active_servers": "活动服务器",
  "uptime": "正常运行时间",
  "s": "附议",
  "ss": "秒钟",
  "m": "分钟",
  "mm": "分钟",
  "h": "小时",
  "hh": "时数",
  "d": "天",
  "dd": "天数",
  "w": "周",
  "ww": "周数"
}
